uawidgets/__init__.py
uawidgets/attrs_widget.py
uawidgets/call_method_dialog.py
uawidgets/get_node_dialog.py
uawidgets/logger.py
uawidgets/new_node_dialogs.py
uawidgets/refs_widget.py
uawidgets/resources.py
uawidgets/tree_widget.py
uawidgets/utils.py
opcua_widgets-0.6.1.dist-info/LICENSE
opcua_widgets-0.6.1.dist-info/METADATA
opcua_widgets-0.6.1.dist-info/WHEEL
opcua_widgets-0.6.1.dist-info/top_level.txt
opcua_widgets-0.6.1.dist-info/RECORD
