Metadata-Version: 1.0
Name: opcua-widgets
Version: 0.6.1
Summary: OPC-UA Widgets
Home-page: https://github.com/FreeOpcUa/opcua-widgets
Author: Olivier R-D et al.
Author-email: UNKNOWN
License: GNU General Public License
Platform: UNKNOWN
